MegaCalculator/MegaCalculator.py
MegaCalculator/__init__.py
megacalculator-0.0.1.dist-info/METADATA
megacalculator-0.0.1.dist-info/WHEEL
megacalculator-0.0.1.dist-info/licenses/LICENSE
megacalculator-0.0.1.dist-info/RECORD
