Metadata-Version: 2.1
Name: MegaCalculator
Version: 0.0.1
Summary: A simple calculator package.
Author-email: Milos Cecaric <mcecaric21@gmail.com>
License-File: LICENSE
Classifier: License :: OSI Approved :: MIT License
Classifier: Operating System :: OS Independent
Classifier: Programming Language :: Python :: 3
Requires-Python: >=3.8
